PRELAB_4/TN3/design.sv
// BCD to led 7 doan
module LAB4_TN3(
  input logic [3:0] I,
  output logic [6:0] out
);
  always@(I) begin
    case (I)
      4'b0000: out = 7'b1000000;
      4'b0001: out = 7'b1111001;
      4'b0010: out = 7'b0100100;
      4'b0011: out = 7'b0110000;
      4'b0100: out = 7'b0011001;
      4'b0101: out = 7'b0010010;
	  4'b0110: out = 7'b0000010;
      4'b0111: out = 7'b1111000;
      4'b1000: out = 7'b0000000;
      4'b1001: out = 7'b0010000;
    endcase
  end
 endmodule

PRELAB_4/TN3/testbench.sv
// Code your testbench here
// or browse Examples
// Code your testbench here
// or browse Examples
`timescale 1ns/1ns
module testbench;
  reg[3:0] I;
  wire logic [6:0] out;
  
  LAB4_TN3 dut(.I(I),.out(out));
   initial begin
    $dumpfile("dump.vcd");
    $dumpvars(1);
    I = 4'b0000;
    #5
    I = 4'b0001;
    #5
   	I = 4'b0010;
    #5
    I = 4'b0011;
    #5
    I = 4'b0100;
    #5
    I = 4'b0101;
    #5
    I = 4'b0110;
    #5
    I = 4'b0111;
    #5
    I = 4'b1000;
    #5
    I = 4'b1001;
    #5
    $finish;
  end
    endmodule

PRELAB_4/TN3/dump.vcd
$date
	Mon Nov  7 03:33:18 2022
$end
$version
	QuestaSim Version 2021.3
$end
$timescale
	1ns
$end

$scope module testbench $end
$var reg 4 ! I [3:0] $end
$var wire 1 " out [6] $end
$var wire 1 # out [5] $end
$var wire 1 $ out [4] $end
$var wire 1 % out [3] $end
$var wire 1 & out [2] $end
$var wire 1 ' out [1] $end
$var wire 1 ( out [0] $end
$upscope $end
$enddefinitions $end
#0
$dumpvars
b0 !
0(
0'
0&
0%
0$
0#
1"
$end
#5
b1 !
1(
1%
1$
1#
#10
b10 !
0(
1&
0%
0$
0"
#15
b11 !
0&
1$
#20
b100 !
1(
1%
0#
#25
b101 !
0(
1'
0%
#30
b110 !
0$
#35
b111 !
0'
1%
1$
1#
1"
#40
b1000 !
0%
0$
0#
0"
#45
b1001 !
1$
