LAB_2/lab2_tn2/design.sv
// Code your design here
module lab2_tn2(
	input a,b,c, 
  	output out
); 
  assign out = !((!(a&!b))|(!(a|(b&c))));
        
endmodule

LAB_2/lab2_tn2/testbench.sv
// Code your testbench here
// or browse Examples
`timescale 1ns/1ns
module testbench;
  reg x,y,z;
  wire f;
  
  lab2_tn2 dut(.a(x),.b(y),.c(z),.out(f));
  
  initial begin
    $dumpfile("dump.vcd");
    $dumpvars(1);
    x = 0;
    y = 0;
    z = 0;
    #5
    x = 0;
    y = 0;
    z = 1;
    #5
    x = 0;
    y = 1;
    z = 0;
    #5
    x = 0;
    y = 1;
    z = 1;
    #5
    x = 1;
    y = 0;
    z = 0;
    #5
    x = 1;
    y = 0;
    z = 1;
    #5
    x = 1;
    y = 1;
    z = 0;
    #5
    x = 1;
    y = 1;
    z = 1;
    #5
    x = 0;
    y = 0;
    z = 0;
    #5
    $finish;
  end
    endmodule

LAB_2/lab2_tn1/dump.vcd
$date
	Sun Oct  9 23:51:52 2022
$end
$version
	QuestaSim Version 2021.3
$end
$timescale
	1ns
$end

$scope module testbench $end
$var reg 1 ! x $end
$var reg 1 " y $end
$var reg 1 # z $end
$var wire 1 $ f $end
$upscope $end
$enddefinitions $end
#0
$dumpvars
0!
0"
0#
0$
$end
#5
1#
1$
#10
1"
0#
0$
#15
1#
1$
#20
1!
0"
0#
0$
#25
1#
#30
1"
0#
1$
#35
1#
#40
0!
0"
0#
0$
