LAB_2/lab2_tn6/design.sv
module ic138(
       input logic g,
       input logic g2a,g1a,
  	   input logic x,y,z,w,
  output logic [7:0] y_o,
  output logic y_out);
  reg [2:0] temp;
  assign combine = {x,y,z};
  assign temp ={g,g1a,g2a};
  assign y_0 = 8'b11111111;
  always_comb
    begin
      if (temp == 3'b100)
        begin
          case (combine)
          3'b111: y_o[7] = 1'b0;
          3'b110: y_o[6] = 1'b0;
          3'b101: y_o[5] = 1'b0;
          3'b100: y_o[4] = 1'b0;
          3'b011: y_o[3] = 1'b0;
          3'b010: y_o[2] = 1'b0;
          3'b001: y_o[1] = 1'b0;
          3'b000: y_o[0] = 1'b0;
         default: y_o = 1'b0;
      endcase
        end
      else
        y_o = 1'b0;
    end
  assign y_out = (w&y_o[1])|(w&y_o[2])|(w&y_o[3])|(!w&y_o[5])|(!w&y_o[7]);
endmodule

PRELAB_2/lab2_tn5/testbench.sv
`timescale 1ns/1ns
module testbench;
  reg g;
  reg g2a;
  reg g1a;
  reg x,y,z;
  wire y_o;
  wire y_out;
  ic138 dut(.g(g),.g2a(g2a),.g1a(g1a),.x(x),
            .y(y),.z(z),.y_o(y_o),.y_out(y_out));
initial begin
  $dumpfile("dump.vcd");
  $dumpvars(1);
  g = 1; g2a = 0; g1a = 0;
  x = 0; y = 0;z = 0;
     #5
  g = 1; g2a = 0; g1a = 0;
  x = 0; y = 0;z = 1;
  	#5
  g = 1; g2a = 0; g1a = 0;
  x = 0; y = 1;z = 0;
       #5
  g = 1; g2a = 0; g1a = 0;
  x = 0; y = 1;z = 1;
       #5
  g = 1; g2a = 0; g1a = 0;
  x = 1; y = 0;z = 0;
    #5
  g = 1; g2a = 0; g1a = 0;
  x = 1; y = 0;z = 1;
    #5
  g = 1; g2a = 0; g1a = 0;
  x = 1; y = 1;z = 0;
    #5
  g = 1; g2a = 0; g1a = 0;
  x = 1; y = 1;z = 1;

  #5
  $finish;
end
endmodule

LAB_2/lab2_tn5/dump.vcd
$date
	Mon Oct 10 10:05:52 2022
$end
$version
	QuestaSim Version 2021.3
$end
$timescale
	1ns
$end

$scope module testbench $end
$var reg 1 ! g $end
$var reg 1 " g2a $end
$var reg 1 # g1a $end
$var reg 1 $ x $end
$var reg 1 % y $end
$var reg 1 & z $end
$var wire 1 ' y_o $end
$var wire 1 ( y_out $end
$upscope $end
$enddefinitions $end
#0
$dumpvars
1!
0"
0#
0$
0%
0&
0'
1(
$end
#5
1&
#10
1%
0&
#15
1&
#20
1$
0%
0&
#25
1&
#30
1%
0&
#35
1&
